pycaptcha_guard_playwright/__init__.py
pycaptcha_guard_playwright/base_page.py
pycaptcha_guard_playwright/captcha.py
pycaptcha_guard_playwright/capsolver_solution/__init__.py
pycaptcha_guard_playwright/capsolver_solution/google_recaptcha.py
pycaptcha_guard_playwright/capsolver_solution/textcaptcha.py
pycaptcha_guard_playwright/captcha_locators/__init__.py
pycaptcha_guard_playwright/captcha_locators/google_recaptcha_locator.py
pycaptcha_guard_playwright/captcha_locators/textcaptcha_locator.py
pycaptcha_guard_playwright/common_components/__init__.py
pycaptcha_guard_playwright/common_components/constants.py
pycaptcha_guard_playwright/nopecha_solution/__init__.py
pycaptcha_guard_playwright/nopecha_solution/google_recaptcha.py
pycaptcha_guard_playwright/nopecha_solution/textcaptcha.py
pycaptcha_guard_playwright-1.0.4.dist-info/METADATA
pycaptcha_guard_playwright-1.0.4.dist-info/WHEEL
pycaptcha_guard_playwright-1.0.4.dist-info/top_level.txt
pycaptcha_guard_playwright-1.0.4.dist-info/RECORD
