Metadata-Version: 2.4
Name: pycaptcha-guard-playwright
Version: 1.0.4
Summary: Solve any kind of captcha like human
Author: MurtazaA
License: MIT
Requires-Python: >=3.9
Requires-Dist: nopecha>=1.0.8
Requires-Dist: playwright>=1.35
Requires-Dist: pillow==10.1.0
Requires-Dist: pyautogui==0.9.54
Requires-Dist: capsolver>=1.0.7
Dynamic: author
Dynamic: description
Dynamic: description-content-type
Dynamic: license
Dynamic: requires-dist
Dynamic: requires-python
Dynamic: summary
